foolai/__init__.py
foolai/__version__.py
foolai/banner.py
foolai/config.py
foolai/fool.py
foolai/imageclassification/adversarial/__init__.py
foolai/imageclassification/adversarial/attacker.py
foolai/imageclassification/adversarial/examples.py
foolai/imageclassification/adversarial/fgsm.py
foolai/main.py
foolai/result.py
foolai/target.py
foolai/utils.py
foolai-0.0.1.dist-info/LICENSE
foolai-0.0.1.dist-info/METADATA
foolai-0.0.1.dist-info/WHEEL
foolai-0.0.1.dist-info/entry_points.txt
foolai-0.0.1.dist-info/RECORD
