Metadata-Version: 2.1
Name: foolai
Version: 0.0.1
Summary: Fool AI Framework
Author: Hideki Ishiguro
Author-email: hideckies@gmail.com
Requires-Python: >=3.9,<3.13
Classifier: Programming Language :: Python :: 3
Classifier: Programming Language :: Python :: 3.9
Classifier: Programming Language :: Python :: 3.10
Classifier: Programming Language :: Python :: 3.11
Requires-Dist: huggingface-hub (>=0.16.4,<0.17.0)
Requires-Dist: torch (>=2.0.0,!=2.0.1)
Requires-Dist: torchvision (==0.15.1)
Requires-Dist: transformers (>=4.32.1,<5.0.0)
Requires-Dist: typer[all] (>=0.9.0,<0.10.0)
